ciscoris/__init__.py
ciscoris/ris.py
ciscoris-0.0.5.dist-info/METADATA
ciscoris-0.0.5.dist-info/RECORD
ciscoris-0.0.5.dist-info/WHEEL
ciscoris-0.0.5.dist-info/top_level.txt
