Metadata-Version: 2.1
Name: ciscoris
Version: 0.0.5
Summary: Cisco CUCM RIS Library. Simple to use.
Home-page: https://github.com/levensailor/ciscoris
Author: Jeff Levensailor
Author-email: jeff@levensailor.com
License: MIT
Keywords: Cisco,Call Manager,CUCM,RIS,LogCollection,VoIP
Platform: UNKNOWN
Classifier: Programming Language :: Python :: 3
Classifier: License :: OSI Approved :: MIT License
Classifier: Operating System :: OS Independent
